[
    {
        "name": "Dhruv Saoji",
        "profile": "https://storage.googleapis.com/download/storage/v1/b/ktp-site.appspot.com/o/pfps%2F128_0MWk6hSwUUNZNCfdqEuwmVdBeAG3.jpg?generation=1677029397049813&alt=media"
    },
    {
        "name": "Andrew Gao",
        "profile": "https://storage.googleapis.com/download/storage/v1/b/ktp-site.appspot.com/o/pfps%2F128_0RPQEp7tpQhjyp60Lwe9SmMkfmD3.jpg?generation=1719254301221683&alt=media"
    },
    {
        "name": "Akash Vikram Shroff",
        "profile": ""
    },
    {
        "name": "Nicholas Perry",
        "profile": "https://storage.googleapis.com/download/storage/v1/b/ktp-site.appspot.com/o/pfps%2F128_0qLC6qufaMQcCmgYfbsZRXWCpPZ2.jpg?generation=1682559670250568&alt=media"
    },
    {
        "name": "Andre Tsai",
        "profile": "https://storage.googleapis.com/download/storage/v1/b/ktp-site.appspot.com/o/pfps%2F128_1Ftz5q5nSKQ81obhVnqIa0K84Kt2.jpg?generation=1674758514731510&alt=media"
    },
    {
        "name": "Vikram Srikishan",
        "profile": "https://storage.googleapis.com/download/storage/v1/b/ktp-site.appspot.com/o/pfps%2F128_1LQz20nkj8PxoHHs7URBCDWZkS02.jpg?generation=1673927580159229&alt=media"
    },
    {
        "name": "Blake Hu",
        "profile": "https://storage.googleapis.com/download/storage/v1/b/ktp-site.appspot.com/o/pfps%2F128_1fGPgXHylWTDzSxi7k6ovHNaXC03.jpg?generation=1684514599754146&alt=media"
    },
    {
        "name": "Kevin Kaspar",
        "profile": ""
    },
    {
        "name": "Annika Anandsongkit",
        "profile": "https://storage.googleapis.com/download/storage/v1/b/ktp-site.appspot.com/o/pfps%2F128_3Q5yFDzc6tfuCxI3kLhzYlcNHlL2.jpg?generation=1673922957217052&alt=media"
    },
    {
        "name": "Gavin Chung",
        "profile": "https://storage.googleapis.com/download/storage/v1/b/ktp-site.appspot.com/o/pfps%2F128_3Y6OlutvftYnypWPSlanTJb90gx2.jpg?generation=1732559664179086&alt=media"
    },
    {
        "name": "Michael Hernandez-Thomas",
        "profile": "https://storage.googleapis.com/download/storage/v1/b/ktp-site.appspot.com/o/pfps%2F128_3vaK3JHhVSagQVsc59xqsDrpT872.jpg?generation=1733612716589670&alt=media"
    },
    {
        "name": "Tatum Thomas",
        "profile": "https://storage.googleapis.com/download/storage/v1/b/ktp-site.appspot.com/o/pfps%2F128_4JYhW5QreoOcm3ze7Pa6GGcLams2.jpg?generation=1680968263861072&alt=media"
    },
    {
        "name": "Alex Feng",
        "profile": ""
    },
    {
        "name": "Daniela Aves",
        "profile": "https://storage.googleapis.com/download/storage/v1/b/ktp-site.appspot.com/o/pfps%2F128_4xX1j2n1A9Xvm1nTUQM5fAnpqOt1.jpg?generation=1737515046078288&alt=media"
    },
    {
        "name": "Josh Prunty",
        "profile": "https://storage.googleapis.com/download/storage/v1/b/ktp-site.appspot.com/o/pfps%2F128_4ytousLb9oR61eVjeDKPUfFvKoi2.jpg?generation=1681081947072829&alt=media"
    },
    {
        "name": "Abigail Anton",
        "profile": "https://storage.googleapis.com/download/storage/v1/b/ktp-site.appspot.com/o/pfps%2F128_5gsiLketV0Yf6NpbcyXepHJ48L02.jpg?generation=1738636744753231&alt=media"
    },
    {
        "name": "Jaimie Hong",
        "profile": "https://storage.googleapis.com/download/storage/v1/b/ktp-site.appspot.com/o/pfps%2F128_6pdCIQ3VPTdFxS02zF711RHDTRa2.jpg?generation=1705270719609962&alt=media"
    },
    {
        "name": "Joseph Shim",
        "profile": "https://storage.googleapis.com/download/storage/v1/b/ktp-site.appspot.com/o/pfps%2F128_7CAXnUWYG0UwgW55Zxu469ObII53.jpg?generation=1705263861559388&alt=media"
    },
    {
        "name": "Cyrus Nadizadeh",
        "profile": "https://storage.googleapis.com/download/storage/v1/b/ktp-site.appspot.com/o/pfps%2F128_7NCy6qyxl6hAQj9Wo1qnXeM1FKt1.jpg?generation=1737512415796486&alt=media"
    },
    {
        "name": "Nicholas Tsung",
        "profile": ""
    },
    {
        "name": "Benjamin Isaac",
        "profile": ""
    },
    {
        "name": "Trayi Sharma",
        "profile": ""
    },
    {
        "name": "David Sotir",
        "profile": ""
    },
    {
        "name": "Rachel Li",
        "profile": "https://storage.googleapis.com/download/storage/v1/b/ktp-site.appspot.com/o/pfps%2F128_9WfuK0X5DGRcWgdhE95UfJo3b4Z2.jpg?generation=1739486549137778&alt=media"
    },
    {
        "name": "Damien Koh",
        "profile": ""
    },
    {
        "name": "Eagan Notokusumo",
        "profile": "https://storage.googleapis.com/download/storage/v1/b/ktp-site.appspot.com/o/pfps%2F128_9vJyDpDgRHhgfYN5ndGaJCc2xB92.jpg?generation=1675812190525078&alt=media"
    },
    {
        "name": "Jonathan Chan",
        "profile": "https://storage.googleapis.com/download/storage/v1/b/ktp-site.appspot.com/o/pfps%2F128_AAeUnlgo3yY54FM4vrBHtpg8dnl1.jpg?generation=1676929826704975&alt=media"
    },
    {
        "name": "Tony Luo",
        "profile": ""
    },
    {
        "name": "Kathy Cui",
        "profile": "https://storage.googleapis.com/download/storage/v1/b/ktp-site.appspot.com/o/pfps%2F128_BYPNCSGmxNQ3smiiuI9JgcePy6C3.jpg?generation=1708851892113680&alt=media"
    },
    {
        "name": "Mia Cheng",
        "profile": "https://storage.googleapis.com/download/storage/v1/b/ktp-site.appspot.com/o/pfps%2F128_BtFJTVKqT9cvwgUWHyoEauxJN0w2.jpg?generation=1674179702853032&alt=media"
    },
    {
        "name": "Ella Cutler",
        "profile": ""
    },
    {
        "name": "Alex Shen",
        "profile": ""
    },
    {
        "name": "Christian Fikre",
        "profile": ""
    },
    {
        "name": "Arthur Zakrzewski",
        "profile": "https://storage.googleapis.com/download/storage/v1/b/ktp-site.appspot.com/o/pfps%2F128_DZtQncnlirfDR6beHFMFS0vANKb2.jpg?generation=1738032395489053&alt=media"
    },
    {
        "name": "Leilani Kulkarni",
        "profile": "https://storage.googleapis.com/download/storage/v1/b/ktp-site.appspot.com/o/pfps%2F128_DfETbrfRTSSVI3xT5VUcJmQtOGg2.jpg?generation=1712883897349596&alt=media"
    },
    {
        "name": "Jordan Chu",
        "profile": "https://storage.googleapis.com/download/storage/v1/b/ktp-site.appspot.com/o/pfps%2F128_DnYpa7kyvBSa3ISVqUNDVHwpleE2.jpg?generation=1705264135694377&alt=media"
    },
    {
        "name": "Lauren Tan",
        "profile": "https://storage.googleapis.com/download/storage/v1/b/ktp-site.appspot.com/o/pfps%2F128_E7g1SSXf8of929ehBLRVGSIeaSQ2.jpg?generation=1713197826488563&alt=media"
    },
    {
        "name": "Muhammad Tahir",
        "profile": "https://storage.googleapis.com/download/storage/v1/b/ktp-site.appspot.com/o/pfps%2F128_EK90HjpVAkfyOhNsXTmaNs9qLwN2.jpg?generation=1738032385203997&alt=media"
    },
    {
        "name": "Amelia Hasting",
        "profile": "https://storage.googleapis.com/download/storage/v1/b/ktp-site.appspot.com/o/pfps%2F128_FPxXqeDZTASpGeD3KxM2J1QJ05T2.jpg?generation=1717530488958793&alt=media"
    },
    {
        "name": "Natalie Hong",
        "profile": "https://storage.googleapis.com/download/storage/v1/b/ktp-site.appspot.com/o/pfps%2F128_Fue3FCehY4bJ6Dc02J5SGcfgaGA2.jpg?generation=1705349430226556&alt=media"
    },
    {
        "name": "Rishi Garg",
        "profile": "https://storage.googleapis.com/download/storage/v1/b/ktp-site.appspot.com/o/pfps%2F128_G6uNpilxhshGvAHdxRb34bmjahG3.jpg?generation=1728067052971453&alt=media"
    },
    {
        "name": "Nicole Liu ",
        "profile": "https://storage.googleapis.com/download/storage/v1/b/ktp-site.appspot.com/o/pfps%2F128_GQDd80czlYWgDRoVFdRg0k0zAHG2.jpg?generation=1705982328229022&alt=media"
    },
    {
        "name": "Isaac Winoto",
        "profile": ""
    },
    {
        "name": "Julie Park",
        "profile": ""
    },
    {
        "name": "Nhat Nam Nguyen",
        "profile": ""
    },
    {
        "name": "Anitej Siluveru",
        "profile": "https://storage.googleapis.com/download/storage/v1/b/ktp-site.appspot.com/o/pfps%2F128_HOjIVdpQy3aDU0JkGFKOV490Ucm2.jpg?generation=1674181851559288&alt=media"
    },
    {
        "name": "Kelly Meng",
        "profile": "https://storage.googleapis.com/download/storage/v1/b/ktp-site.appspot.com/o/pfps%2F128_IbfuuUyOYMhFfkSOmgFJb27aybj2.jpg?generation=1674177401853647&alt=media"
    },
    {
        "name": "Zacaria Bahojb Nouri",
        "profile": "https://storage.googleapis.com/download/storage/v1/b/ktp-site.appspot.com/o/pfps%2F128_IomYJWjEfOWnYf3VqihYqjLF3MJ3.jpg?generation=1684991990407215&alt=media"
    },
    {
        "name": "Finn McMillan",
        "profile": "https://storage.googleapis.com/download/storage/v1/b/ktp-site.appspot.com/o/pfps%2F128_J8ScAs0xBJRi7O4QdwW98f3Lnnf2.jpg?generation=1738796518787550&alt=media"
    },
    {
        "name": "Nico Biabani",
        "profile": ""
    },
    {
        "name": "Shervin Naini",
        "profile": ""
    }
]